README.md
setup.py
aiohttp_route/__init__.py
aiohttp_route.egg-info/PKG-INFO
aiohttp_route.egg-info/SOURCES.txt
aiohttp_route.egg-info/dependency_links.txt
aiohttp_route.egg-info/requires.txt
aiohttp_route.egg-info/top_level.txt