Metadata-Version: 1.1
Name: aiohttp-route
Version: 0.0.2
Summary: @route decorator for aiohttp.web
Home-page: https://github.com/panagiks/aiohttp-route/
Author: Kolokotronis Panagiotis
Author-email: UNKNOWN
License: MIT
Platform: UNKNOWN
Classifier: License :: OSI Approved :: MIT License
Classifier: Intended Audience :: Developers
Classifier: Programming Language :: Python
Classifier: Programming Language :: Python :: 3
Classifier: Programming Language :: Python :: 3.5
Classifier: Programming Language :: Python :: 3.6
Classifier: Topic :: Internet :: WWW/HTTP
Classifier: Framework :: AsyncIO
